ticktock/__init__.py
ticktock/clocks.py
ticktock/collection.py
ticktock/data.py
ticktock/py.typed
ticktock/renderers.py
ticktock/std.py
ticktock/timers.py
ticktock/utils.py
py_ticktock-0.1.2.dist-info/LICENSE
py_ticktock-0.1.2.dist-info/METADATA
py_ticktock-0.1.2.dist-info/WHEEL
py_ticktock-0.1.2.dist-info/top_level.txt
py_ticktock-0.1.2.dist-info/RECORD
