Metadata-Version: 2.1
Name: py-ticktock
Version: 0.1.2
Summary: Simple Python code metering library.
Home-page: UNKNOWN
License: UNKNOWN
Project-URL: Bug Tracker, https://github.com/victorbenichoux/ticktock/issues
Project-URL: Documentation, https://victorbenichoux.github.io/tickto/
Project-URL: Source Code, https://github.com/victorbenichoux/ticktock
Platform: UNKNOWN
Classifier: Programming Language :: Python :: 3
Classifier: Programming Language :: Python :: 3.7
Classifier: Programming Language :: Python :: 3.8
Classifier: Programming Language :: Python :: 3.9
Requires-Dist: psutil
